dlr/__init__.py
dlr/api.py
dlr/dlr_model.py
dlr/libpath.py
dlr/metadata.py
dlr/neologger.py
dlr/counter/__init__.py
dlr/counter/config.py
dlr/counter/deviceinfo.py
dlr/counter/phone_home.py
dlr/counter/system.py
dlr/counter/utils/__init__.py
dlr/counter/utils/helper.py
dlr/counter/utils/resturlutils.py
test/__init__.py
test/test_phone_home.py
dlr-1.10.0.dist-info/METADATA
dlr-1.10.0.dist-info/WHEEL
dlr-1.10.0.dist-info/top_level.txt
dlr-1.10.0.dist-info/RECORD
