Metadata-Version: 2.1
Name: dlr
Version: 1.10.0
Summary: Common runtime for machine learning models compiled by         AWS SageMaker Neo, TVM, or TreeLite.
Home-page: https://github.com/neo-ai/neo-ai-dlr
Author: AWS Neo
Author-email: aws-neo-ai@amazon.com
License: Apache-2.0
Platform: UNKNOWN
Classifier: Development Status :: 5 - Production/Stable
Classifier: Topic :: Utilities
Classifier: License :: OSI Approved :: Apache Software License
Requires-Python: >=3.5
Requires-Dist: numpy
Requires-Dist: requests
Requires-Dist: distro
